contract_schema/__init__.py
contract_schema/card.py
contract_schema/contract.py
contract_schema/document.py
contract_schema/loader.py
contract_schema/parser.py
contract_schema/utils.py
contract_schema/validator.py
contract_schema/schemas/__init__.py
contract_schema/schemas/analytic_schema.json
contract_schema/schemas/contract_meta_schema.json
contract_schema/schemas/model_schema.json
contract_schema-1.0.0.dist-info/licenses/LICENSE.md
contract_schema-1.0.0.dist-info/METADATA
contract_schema-1.0.0.dist-info/WHEEL
contract_schema-1.0.0.dist-info/top_level.txt
contract_schema-1.0.0.dist-info/RECORD
