Metadata-Version: 2.4
Name: contract-schema
Version: 1.0.0
Summary: Standardised inputs and outputs based on contract files.
Author-email: Zachary Szewczyk <zacjszewczyk@gmail.com>
License: License
Project-URL: Homepage, https://github.com/zacjszewczyk/contract-schema
Project-URL: Issues, https://github.com/zacjszewczyk/contract-schema/issues
Classifier: Programming Language :: Python :: 3
Classifier: Operating System :: OS Independent
Requires-Python: >=3.8
License-File: LICENSE.md
Provides-Extra: analytic
Requires-Dist: pandas>=1.0; extra == "analytic"
Dynamic: license-file
